<?xml version="1.0" encoding="utf-8"?>
<!-- EN-Revision: 330617 Maintainer: none Status: ready -->
<itemizedlist xmlns="http://docbook.org/ns/docbook"
xmlns:xlink="http://www.w3.org/1999/xlink">
 <listitem>
  <para>
   &null;, no caso em que o fuso horário padrão será usado, como especificado na
   configuração de inicialização <link linkend="ini.date.timezone">date.timezone</link> ou
   através da função <function>date_default_timezone_set</function> e como
   retornado pela função <function>date_default_timezone_get</function>.
  </para>
 </listitem>
 <listitem>
  <para>
   Um objeto <classname>IntlTimeZone</classname>, que será utilizado diretamente.
  </para>
 </listitem>
 <listitem>
  <para>
   Um objeto <classname>DateTimeZone</classname>. O identificador será extraído
   e um objeto de fuso horário ICU será criado; o fuso horário será provido
   pelo banco de dados da ICUʼs e não pelo do PHP.
  </para>
 </listitem>
 <listitem>
  <para>
   Uma <type>string</type>, que deve ser um identificador de fuso horário ICU válido.
   Consulte <function>IntlTimeZone::createTimeZoneIDEnumeration</function>. Deslocamentos
   como <literal>"GMT+08:30"</literal> também são aceitos.
  </para>
 </listitem>
</itemizedlist>
